attr_descriptions/__init__.py
attr_descriptions-0.1.3.dist-info/LICENSE
attr_descriptions-0.1.3.dist-info/METADATA
attr_descriptions-0.1.3.dist-info/WHEEL
attr_descriptions-0.1.3.dist-info/top_level.txt
attr_descriptions-0.1.3.dist-info/RECORD
