Metadata-Version: 2.1
Name: attr-descriptions
Version: 0.1.3
Summary: A mini-module that helps to add descriptions to attrs attributes.
Home-page: https://github.com/deniz195/attr-descriptions
Author: Deniz Bozyigit
Author-email: deniz195@gmail.com
License: MIT License
Requires-Dist: attrs
Requires-Dist: cattrs
